databatch_lib/__init__.py
databatch_lib/dataloadbatch.py
databatch_lib/dataretrievalbatch.py
databatch_lib/db_instances_.py
databatch_lib/config/__init__.py
databatch_lib/config/config_loader.py
databatch_lib/utils/__init__.py
databatch_lib/utils/constants.py
databatch_lib/utils/file_reader.py
databatch_lib-0.1.2.dist-info/licenses/LICENSE
databatch_lib-0.1.2.dist-info/METADATA
databatch_lib-0.1.2.dist-info/WHEEL
databatch_lib-0.1.2.dist-info/top_level.txt
databatch_lib-0.1.2.dist-info/RECORD
